torch_code_tracing/__init__.py
torch_code_tracing-0.1.1.dist-info/licenses/LICENSE
torch_code_tracing-0.1.1.dist-info/METADATA
torch_code_tracing-0.1.1.dist-info/WHEEL
torch_code_tracing-0.1.1.dist-info/top_level.txt
torch_code_tracing-0.1.1.dist-info/RECORD
