Metadata-Version: 2.4
Name: torch-code-tracing
Version: 0.1.1
Summary: Code tracing for PyTorch models
Author-email: Justin Chu <justinchu@microsoft.com>
License-Expression: MIT
Project-URL: Issues, https://github.com/justinchuby/torch-code-tracing/issues
Project-URL: Repository, https://github.com/justinchuby/torch-code-tracing
Requires-Python: >=3.10
License-File: LICENSE
Requires-Dist: torch
Dynamic: license-file
